{
    "volume": {
        "right": 3076.69,
        "left": 3118.32
    },
    "hist": {
        "HU": [
            -1100,
            -1090,
            -1080,
            -1070,
            -1060,
            -1050,
            -1040,
            -1030,
            -1020,
            -1010,
            -1000,
            -990,
            -980,
            -970,
            -960,
            -950,
            -940,
            -930,
            -920,
            -910,
            -900,
            -890,
            -880,
            -870,
            -860,
            -850,
            -840,
            -830,
            -820,
            -810,
            -800,
            -790,
            -780,
            -770,
            -760,
            -750,
            -740,
            -730,
            -720,
            -710,
            -700,
            -690,
            -680,
            -670,
            -660,
            -650,
            -640,
            -630,
            -620,
            -610,
            -600,
            -590,
            -580,
            -570,
            -560,
            -550,
            -540,
            -530,
            -520,
            -510,
            -500,
            -490,
            -480,
            -470,
            -460,
            -450,
            -440,
            -430,
            -420,
            -410,
            -400,
            -390,
            -380,
            -370,
            -360,
            -350,
            -340,
            -330,
            -320,
            -310,
            -300,
            -290,
            -280,
            -270,
            -260,
            -250,
            -240,
            -230,
            -220,
            -210,
            -200,
            -190,
            -180,
            -170,
            -160,
            -150,
            -140,
            -130,
            -120,
            -110,
            -100,
            -90,
            -80,
            -70,
            -60,
            -50,
            -40,
            -30,
            -20,
            -10,
            0,
            10,
            20,
            30,
            40,
            50,
            60,
            70,
            80,
            90,
            100,
            110,
            120,
            130,
            140,
            150,
            160,
            170,
            180,
            190,
            200,
            210,
            220,
            230,
            240,
            250,
            260,
            270,
            280,
            290,
            300,
            310
        ],
        "right": [
            0.0,
            0.0,
            0.0,
            0.0,
            0.0,
            0.0,
            0.0,
            0.16,
            0.047,
            0.058,
            0.076,
            0.111,
            0.166,
            0.227,
            0.336,
            0.51,
            0.737,
            1.04,
            1.418,
            1.855,
            2.353,
            2.889,
            3.332,
            3.78,
            4.129,
            4.402,
            4.513,
            4.528,
            4.458,
            4.255,
            4.054,
            3.786,
            3.517,
            3.183,
            2.898,
            2.59,
            2.336,
            2.087,
            1.854,
            1.67,
            1.484,
            1.338,
            1.201,
            1.08,
            0.965,
            0.877,
            0.816,
            0.745,
            0.679,
            0.635,
            0.562,
            0.54,
            0.501,
            0.461,
            0.435,
            0.412,
            0.38,
            0.371,
            0.35,
            0.327,
            0.312,
            0.305,
            0.293,
            0.282,
            0.267,
            0.251,
            0.252,
            0.228,
            0.222,
            0.22,
            0.204,
            0.204,
            0.192,
            0.188,
            0.186,
            0.181,
            0.164,
            0.169,
            0.167,
            0.153,
            0.155,
            0.154,
            0.154,
            0.136,
            0.143,
            0.143,
            0.14,
            0.143,
            0.127,
            0.126,
            0.129,
            0.12,
            0.129,
            0.125,
            0.123,
            0.119,
            0.117,
            0.113,
            0.111,
            0.113,
            0.11,
            0.116,
            0.115,
            0.114,
            0.113,
            0.115,
            0.114,
            0.118,
            0.121,
            0.128,
            0.134,
            0.15,
            0.17,
            0.195,
            0.218,
            0.23,
            0.249,
            0.262,
            0.258,
            0.261,
            0.257,
            0.22,
            0.201,
            0.179,
            0.15,
            0.13,
            0.116,
            0.099,
            0.088,
            0.081,
            0.067,
            0.064,
            0.051,
            0.044,
            0.038,
            0.039,
            0.031,
            0.026,
            0.026,
            0.024,
            0.024
        ],
        "left": [
            0.0,
            0.0,
            0.0,
            0.0,
            0.0,
            0.0,
            0.0,
            0.331,
            0.079,
            0.108,
            0.131,
            0.182,
            0.275,
            0.39,
            0.572,
            0.848,
            1.242,
            1.745,
            2.292,
            3.026,
            3.663,
            4.287,
            4.752,
            5.119,
            5.306,
            5.232,
            5.147,
            4.847,
            4.449,
            4.07,
            3.689,
            3.236,
            2.832,
            2.491,
            2.186,
            1.94,
            1.679,
            1.481,
            1.315,
            1.169,
            1.015,
            0.936,
            0.832,
            0.765,
            0.708,
            0.634,
            0.588,
            0.547,
            0.512,
            0.474,
            0.443,
            0.416,
            0.383,
            0.366,
            0.362,
            0.336,
            0.314,
            0.301,
            0.292,
            0.283,
            0.269,
            0.252,
            0.244,
            0.246,
            0.224,
            0.221,
            0.205,
            0.204,
            0.191,
            0.191,
            0.186,
            0.177,
            0.174,
            0.172,
            0.156,
            0.153,
            0.153,
            0.15,
            0.135,
            0.143,
            0.136,
            0.141,
            0.133,
            0.124,
            0.121,
            0.116,
            0.116,
            0.113,
            0.121,
            0.114,
            0.11,
            0.105,
            0.104,
            0.108,
            0.105,
            0.099,
            0.097,
            0.102,
            0.097,
            0.098,
            0.099,
            0.092,
            0.098,
            0.091,
            0.091,
            0.097,
            0.089,
            0.09,
            0.092,
            0.093,
            0.095,
            0.094,
            0.091,
            0.089,
            0.092,
            0.096,
            0.098,
            0.1,
            0.097,
            0.093,
            0.097,
            0.088,
            0.079,
            0.08,
            0.076,
            0.074,
            0.069,
            0.064,
            0.054,
            0.055,
            0.054,
            0.049,
            0.043,
            0.043,
            0.036,
            0.037,
            0.029,
            0.027,
            0.025,
            0.024,
            0.023
        ]
    },
    "lesion_count": 3,
    "lesion_mask": "/Path/Directory/to/Lesion/Mask",
    "lesion_list": [
        {
            "id": 1,
            "pattern": "GGO",
            "location": "left",
            "volume": 3.28,
            "percentage": 0.06,
            "density": -700,
            "start_slice": 90,
            "end_slice": 96,
            "representative_slice": 93
        },
        {
            "id": 2,
            "pattern": "GGO",
            "location": "left",
            "volume": 1.97,
            "percentage": 0.04,
            "density": -730,
            "start_slice": 90,
            "end_slice": 96,
            "representative_slice": 93
        },
        {
            "id": 3,
            "pattern": "consolidation",
            "location": "right",
            "volume": 32.73,
            "percentage": 0.6,
            "density": -300,
            "start_slice": 100,
            "end_slice": 120,
            "representative_slice": 107
        }
    ]
}